foambo/__init__.py
foambo/analysis.py
foambo/common.py
foambo/config.py
foambo/default_config.py
foambo/docs.py
foambo/metrics.py
foambo/optimize.py
foambo/orchestrate.py
foambo/visualize.py
foambo/templates/visualizer.html
foambo-1.1.3.dist-info/METADATA
foambo-1.1.3.dist-info/WHEEL
foambo-1.1.3.dist-info/entry_points.txt
foambo-1.1.3.dist-info/RECORD
