Metadata-Version: 2.4
Name: foambo
Version: 1.1.3
Summary: Configuration-based Multi-objective Bayesian Optimization on OpenFOAM cases with Ax-platform
Project-URL: Homepage, https://github.com/FoamScience/OpenFOAM-Multi-Objective-Optimization
Project-URL: Bug Tracker, https://github.com/FoamScience/OpenFOAM-Multi-Objective-Optimization/issues
Author-email: Mohammed Elwardi Fadeli <elwardifadeli@gmail.com>
Classifier: Development Status :: 4 - Beta
Classifier: Environment :: GPU
Classifier: Framework :: Dash
Classifier: Intended Audience :: Education
Classifier: Intended Audience :: Science/Research
Classifier: License :: OSI Approved :: MIT License
Classifier: Operating System :: OS Independent
Classifier: Programming Language :: Python :: 3
Classifier: Topic :: Scientific/Engineering :: Artificial Intelligence
Classifier: Topic :: Scientific/Engineering :: Physics
Requires-Python: >=3.10
Requires-Dist: ax-platform==1.1.2
Requires-Dist: colorlog>=6.9.0
Requires-Dist: dash-bootstrap-components>=1.4.2
Requires-Dist: dash>=2.11.1
Requires-Dist: fastapi>=0.118.0
Requires-Dist: foamlib>=1.3.10
Requires-Dist: kaleido>=0.2.1
Requires-Dist: nbformat>=5.10.4
Requires-Dist: omegaconf>=2.3.0
Requires-Dist: prompt-toolkit>=3.0.51
Requires-Dist: pyvista>=0.46.3
Requires-Dist: regex>=2023.6.3
Requires-Dist: rich>=14.0.0
Requires-Dist: tabulate>=0.9.0
Requires-Dist: uvicorn>=0.37.0
